sign/__init__.py
sign/tests/test_inherit.py
sign-0.0.2.dist-info/LICENSE
sign-0.0.2.dist-info/WHEEL
sign-0.0.2.dist-info/METADATA
sign-0.0.2.dist-info/RECORD
